fastbay/__init__.py
fastbay/fastbay.py
fastbay-0.1.dist-info/LICENSE
fastbay-0.1.dist-info/METADATA
fastbay-0.1.dist-info/WHEEL
fastbay-0.1.dist-info/top_level.txt
fastbay-0.1.dist-info/RECORD
