Metadata-Version: 2.1
Name: fastbay
Version: 0.1
Summary: Fast torrent parser from PirateBay.
Home-page: https://github.com/termlt/FastBay
Author: termit (Arsen Anoyan)
Author-email: <anoyan2014@yandex.ru>
License: UNKNOWN
Keywords: python,piratebay,search,parser,parsing,information
Platform: UNKNOWN
Classifier: Intended Audience :: Developers
Classifier: Programming Language :: Python :: 3
Classifier: Operating System :: Unix
Classifier: Operating System :: MacOS :: MacOS X
Classifier: Operating System :: Microsoft :: Windows
Requires-Dist: bs4
Requires-Dist: requests
